{"file":"Followers-C6lwZc35.js","mappings":";;;;;;;;;;;;;;;;;;;;;;;;;;;;;;;;;;;AAQA,UAAM,QAAQ,kBAAkB;AAM1B,UAAA,eAAoB,SAAS,MAAM;AACvC,aAAO,MAAM;AAAA,IAAA,CACd;AACK,UAAA,cAAc,IAAI,EAAE;AAET,QAAI;AAAA,MACnB,EAAE,OAAO,YAAY,MAAM,UAAU;AAAA,MACrC,EAAE,OAAO,oBAAoB,MAAM,UAAU;AAAA,MAC7C,EAAE,OAAO,UAAU,MAAM,UAAU;AAAA,IACpC,CAAA;AACY,QAAI,EAAE,OAAO,iBAAkB,CAAA;AAEtC,UAAA,gBAAgB,SAAS,MAAM;AACnC,aAAO,aAAa,MAAM,OAAO,CAAC,SAAc;AACvC,eAAA,KAAK,KAAK,YAAY,EAAE,SAAS,YAAY,MAAM,aAAa;AAAA,MAAA,CACxE;AAAA,IAAA,CACF;;;;;;;;;;;;;;;;;;;;;;;;;;;;;;;;;;;;;;;;;;;;;;;;;;;;;;;;;;;;;;;;;;;;;;;;;;;;;;;;;;;;;;;;;;;;;;;;;;;;;;;;;;;;;;;;;;;;;;;;;;;;;;;;;;;;;;;;;;;;;;;;;;;;;;;;;;;;;;;;;;;;;;;;;;;;;;;;;;;;;;;;;;;;;;;;;;;;;;;;;;;;;;;;;;;;;;;;;;;;;;;;;;;;;;;;;;;;;;;;;;;;;;;;;;;;;;;;;;;;;;;;;;;;;;;;;;;;;;;;;;;;;;;;;;;;;;;;;;;;;;;;;;;;;;;;;;;;;;;;;;;;;;;;;;;;;;;;;;;;;;;;;;;;;;;;;;;;;;;;;;;;;;;;;;;;;;;;;;;;;;;;;;;;;;;;;;;;;;;;;;;;;;;;;;;;;;;;;;;;;;;;;;;;;;;;;;;;;;;;;;;;;;;;;;;;;;;;;;;;;;;;;;;;;;;;;;;;;;;;;;;;;;;;;;;;;;;;;;;;;;;;;;;;;;;;;;;;;;;;;;;;;;;;;;;;;;;;;;;;;;;;;;;;;;;;;;;;;;;;;;;;;;;;;;;;;;;;;;;;;;;;;;;;;;;;;;;","names":[],"sources":["../../../../pages/apps/userprofile/two/Followers.vue"],"sourcesContent":["<script setup lang=\"ts\">\nimport { ref, onMounted, computed } from 'vue';\nimport { HeartIcon, UsersIcon, TrashIcon } from 'vue-tabler-icons';\n\n// components\nimport ProfileBanner from '@/components/apps/user-profile/ProfileBanner.vue';\nimport { useFollowersStore } from '@/stores/apps/userprofile/followers';\n\nconst store = useFollowersStore();\n\nonMounted(() => {\n  store.fetchFollowers();\n});\n\nconst getfollowers: any = computed(() => {\n  return store.followers;\n});\nconst searchValue = ref('');\n// dropdown data\nconst actionDD = ref([\n  { title: 'Favorite', icon: HeartIcon },\n  { title: 'Edit Friend List', icon: UsersIcon },\n  { title: 'Remove', icon: TrashIcon },\n]);\nconst page = ref({ title: 'Social Profile' });\n\nconst filteredCards = computed(() => {\n  return getfollowers.value.filter((card: any) => {\n    return card.name.toLowerCase().includes(searchValue.value.toLowerCase());\n  });\n});\n</script>\n\n<template>\n  <ProfileBanner />\n  <v-row class=\"justify-content-end mt-5\">\n    <v-col cols=\"12\">\n      <div class=\"d-sm-flex align-center mb-5\">\n        <h3 class=\"text-h3 font-weight-semibold\">\n          Followers\n          <v-chip size=\"x-small\" class=\"ml-2 elevation-0\" variant=\"elevated\" color=\"secondary\">{{\n            filteredCards.length\n          }}</v-chip>\n        </h3>\n        <v-sheet width=\"250\" class=\"ml-0 ml-sm-auto mt-3 mt-sm-0\">\n          <v-text-field\n            color=\"primary\"\n            hide-details\n            variant=\"outlined\"\n            placeholder=\"Search Followers\"\n            density=\"compact\"\n            prepend-inner-icon=\"mdi-magnify\"\n            v-model=\"searchValue\"\n          >\n          </v-text-field>\n        </v-sheet>\n      </div>\n\n      <v-row>\n        <v-col cols=\"12\" md=\"4\" sm=\"6\" v-for=\"(card, i) in filteredCards\" :key=\"i\">\n          <v-card elevation=\"10\">\n            <v-card-text class=\"pa-6\">\n              <div class=\"d-flex align-center gap-3\">\n                <v-avatar size=\"40\">\n                  <img :src=\"card.avatar\" :alt=\"card.avatar\" width=\"40\" />\n                </v-avatar>\n                <div class=\"w-50\">\n                  <h6 class=\"text-h5 font-weight-semibold\">{{ card.name }}</h6>\n                  <span class=\"text-truncate d-flex align-center gap-2 text-grey100\">\n                    <mapPinIcon size=\"14\" />\n                    <span class=\"text-truncate w-50\">{{ card.location }}</span>\n                  </span>\n                </div>\n                <div class=\"ml-auto\">\n                  <v-btn v-if=\"card.follow == 1\" variant=\"outlined\" color=\"primary\">\n                    Followed</v-btn\n                  >\n                  <v-btn v-else color=\"primary\"> Follow</v-btn>\n                </div>\n              </div>\n            </v-card-text>\n          </v-card>\n        </v-col>\n      </v-row>\n    </v-col>\n  </v-row>\n</template>\n"],"version":3}