{"file":"Menus-kiYwjkFF.js","mappings":";;;;;;;;;AAGA,UAAM,QAAQ,IAAI;AAAA,MAChB,EAAE,OAAO,WAAW;AAAA,MACpB,EAAE,OAAO,WAAW;AAAA,MACpB,EAAE,OAAO,WAAW;AAAA,MACpB,EAAE,OAAO,aAAa;AAAA,IAAA,CACvB;AAEK,UAAA,YAAY,IAAI,CAAC,OAAO,UAAU,SAAS,OAAO,QAAQ,CAAC;AACjE,UAAM,WAAW,IAAI;;;;;;;;;;;;;;;;;;;;;;;;;;;;;;;;;;;;;;;;;;;;;;;;;;;;;;;;;;;;;;;;;;;;;;;;;;;;;;;;;;;;;;;;;;;;;;;;;;;;;;;;;;;;;;;;;;;;;;;;;;;;;;;;;;;;;;;;;;;;;;;ACTrB,UAAM,QAAQ,IAAI;AAAA,MAChB,EAAE,OAAO,WAAW;AAAA,MACpB,EAAE,OAAO,WAAW;AAAA,MACpB,EAAE,OAAO,WAAW;AAAA,MACpB,EAAE,OAAO,aAAa;AAAA,IAAA,CACvB;;;;;;;;;;;;;;;;;;;;;;;;;;;;;;;;;;;;;;;;;;;;;;;;;;;;;;;;;;;;;;;;;;;;;;;;;;;;;;;;;;;;;;;;;;;;;;;;;;;;;;;;;;;;;;;;;;;;;;;;;;;;;;;;;;ACLD,UAAM,QAAQ,IAAI;AAAA,MAChB,EAAE,OAAO,WAAW;AAAA,MACpB,EAAE,OAAO,WAAW;AAAA,MACpB,EAAE,OAAO,WAAW;AAAA,MACpB,EAAE,OAAO,aAAa;AAAA,IAAA,CACvB;AACU,eAAA;;;;;;;;;;;;;;;;;;;;;;;;;;;;;;;;;;;;;;;;;;;;;;;;;;;;;;;;;;;;;;;;;;;;;;;;;;;;;;;;;;;;;;;;;;;;;;;;;;;;;;;;;;;;;;;;;;;;;;;;;;;;;;;;;;;;;;;;;;;;;;;;;;;;;;;;;;;;;;;;;;;;ACNL,UAAA,MAAM,IAAI,IAAI;AACd,UAAA,OAAO,IAAI,KAAK;AAChB,UAAA,UAAU,IAAI,KAAK;AACnB,UAAA,QAAQ,IAAI,IAAI;;;;;;;;;;;;;;;;;;;;;;;;;;;;;;;;;;;;;;;;;;;;;;;;;;;;;;;;;;;;;;;;;;;;;;;;;;;;;;;;;;;;;;;;;;;;;;;;;;;;;;;;;;;;;;;;;;;;;;;;;;;;;;;;;;;;;;;;;;;;;;;;;;;;;;;;;;;;;;;;;;;;;;;;;;;;;;;;;;;;;;;;;;;;;;;;;;;;;;;;;;;;;;;;;;;;;;;;;;;;;;;;;;;;;;;;;;;;;;;;;;;;;;;;;;;;;;;;;;;;;;;;;;;;;;;;;;;;;;;;;;;;;;;;;;;;;;;;;;;;;;;;;;;;;;;;;;;;;;;;;;;;;;;;;;;;;;;;;;;;;;;;;;;;;;;;;;;;;;;;;;;;;;;;;;;;;;;;;;;;;;;;;;;;;;;;;;;;;;;;;;;;;;;;;;;;;;;;;;;;;;;;;;;;;;;;;;;;;;;;;;;;;;;;;;ACOtB,UAAM,OAAO,IAAI,EAAE,OAAO,SAAS;AACnC,UAAM,cAAc,IAAI;AAAA,MACtB;AAAA,QACE,MAAM;AAAA,QACN,UAAU;AAAA,QACV,MAAM;AAAA,MACR;AAAA,MACA;AAAA,QACE,MAAM;AAAA,QACN,UAAU;AAAA,QACV,MAAM;AAAA,MAAA;AAAA,IACR,CACD;;;;;;;;;;;;;;;;;;;;;;;;;;;;;;;;;;;;;;;;;;;;;;;;;;;;;;;;;;;;;;;;;;;;;;;;;;;;;;;;;;;;;;;;;;;;;;;;;;;;;;;;;;;;;;;;;;;;;;;;;;;;;;;;;;;;;;;;;;;;;;;;;;;;;;;;;;;;;;;;;;;;;;;;;;;;;;;;;;;;;;;;;;;;;;;;;;;;;;;;;;;;;;;;;;;;;;;;;;;;;;;;;;;;;;;;;;;;;;;;;;;;;;;;;;;;;;;;;;;;;;;;;;;;;;;;;;;;;;;;;;;;;;;;;;;;","names":[],"sources":["../../../../components/ui-components/menus/MenusAnchor.vue","../../../../components/ui-components/menus/MenusHover.vue","../../../../components/ui-components/menus/MenusActivatorTooltip.vue","../../../../components/ui-components/menus/MenusPopover.vue","../../../../pages/ui-components/Menus.vue"],"sourcesContent":["<script setup lang=\"ts\">\nimport { ref } from 'vue';\n\nconst items = ref([\n  { title: 'Click Me' },\n  { title: 'Click Me' },\n  { title: 'Click Me' },\n  { title: 'Click Me 2' },\n]);\n\nconst locations = ref(['top', 'bottom', 'start', 'end', 'center']);\nconst location = ref();\n</script>\n\n<template>\n  <div class=\"text-center mt-4\">\n    <v-select v-model=\"location\" :items=\"locations\" label=\"Location\"></v-select>\n    <v-menu :location=\"location\">\n      <template v-slot:activator=\"{ props }\">\n        <v-btn color=\"primary\" dark v-bind=\"props\" class=\"px-4 rounded-pill\"> Dropdown </v-btn>\n      </template>\n\n      <v-list>\n        <v-list-item v-for=\"(item, index) in items\" :key=\"index\">\n          <v-list-item-title>{{ item.title }}</v-list-item-title>\n        </v-list-item>\n      </v-list>\n    </v-menu>\n  </div>\n</template>\n","<script setup lang=\"ts\">\nimport { ref } from 'vue';\nconst items = ref([\n  { title: 'Click Me' },\n  { title: 'Click Me' },\n  { title: 'Click Me' },\n  { title: 'Click Me 2' },\n]);\n</script>\n\n<template>\n  <div class=\"text-center mt-4\">\n    <v-menu open-on-hover>\n      <template v-slot:activator=\"{ props }\">\n        <v-btn color=\"secondary\" v-bind=\"props\" class=\"px-4 rounded-pill\"> Dropdown </v-btn>\n      </template>\n\n      <v-list>\n        <v-list-item v-for=\"(item, index) in items\" :key=\"index\">\n          <v-list-item-title>{{ item.title }}</v-list-item-title>\n        </v-list-item>\n      </v-list>\n    </v-menu>\n  </div>\n</template>\n","<script setup lang=\"ts\">\nimport { ref, mergeProps } from 'vue';\nconst items = ref([\n  { title: 'Click Me' },\n  { title: 'Click Me' },\n  { title: 'Click Me' },\n  { title: 'Click Me 2' },\n]);\nmergeProps();\n</script>\n\n<template>\n  <div class=\"text-center mt-4\">\n    <v-menu>\n      <template v-slot:activator=\"{ props: menu }\">\n        <v-tooltip anchor=\"top\">\n          <template v-slot:activator=\"{ props: tooltip }\">\n            <v-btn color=\"primary\" v-bind=\"mergeProps(menu, tooltip)\" class=\"px-4 rounded-pill\">\n              Dropdown w/ Tooltip\n            </v-btn>\n          </template>\n          <span>I'm A Tooltip</span>\n        </v-tooltip>\n      </template>\n      <v-list>\n        <v-list-item v-for=\"(item, index) in items\" :key=\"index\">\n          <v-list-item-title>{{ item.title }}</v-list-item-title>\n        </v-list-item>\n      </v-list>\n    </v-menu>\n  </div>\n</template>\n","<script setup lang=\"ts\">\nimport { ref } from 'vue';\nconst fav = ref(true);\nconst menu = ref(false);\nconst message = ref(false);\nconst hints = ref(true);\n</script>\n\n<template>\n  <div class=\"text-center mt-4\">\n    <v-menu v-model=\"menu\" :close-on-content-click=\"false\" anchor=\"top\">\n      <template v-slot:activator=\"{ props }\">\n        <v-btn color=\"secondary\" v-bind=\"props\" class=\"px-4 rounded-pill\"> Menu as Popover </v-btn>\n      </template>\n\n      <v-card min-width=\"300\">\n        <v-list>\n          <v-list-item\n            prepend-avatar=\"https://cdn.vuetifyjs.com/images/john.jpg\"\n            title=\"John Leider\"\n            subtitle=\"Founder of Vuetify\"\n          >\n            <template v-slot:append>\n              <v-btn\n                variant=\"text\"\n                :class=\"fav ? 'text-primary' : ''\"\n                icon=\"mdi-heart\"\n                @click=\"fav = !fav\"\n                flat\n              ></v-btn>\n            </template>\n          </v-list-item>\n        </v-list>\n\n        <v-divider></v-divider>\n\n        <v-list>\n          <v-list-item>\n            <v-switch\n              v-model=\"message\"\n              color=\"primary\"\n              label=\"Enable messages\"\n              hide-details\n              class=\"pl-2\"\n            ></v-switch>\n          </v-list-item>\n\n          <v-list-item>\n            <v-switch\n              v-model=\"hints\"\n              color=\"primary\"\n              label=\"Enable hints\"\n              hide-details\n              class=\"pl-2\"\n            ></v-switch>\n          </v-list-item>\n        </v-list>\n\n        <v-card-actions>\n          <v-spacer></v-spacer>\n\n          <v-btn text @click=\"menu = false\" flat> Cancel </v-btn>\n          <v-btn color=\"primary\" text @click=\"menu = false\" flat> Save </v-btn>\n        </v-card-actions>\n      </v-card>\n    </v-menu>\n  </div>\n</template>\n","<script setup lang=\"ts\">\nimport { ref } from 'vue';\n// common components\nimport BaseBreadcrumb from '@/components/shared/BaseBreadcrumb.vue';\nimport UiParentCard from '@/components/shared/UiParentCard.vue';\nimport UiChildCard from '@/components/shared/UiChildCard.vue';\n\nimport MenusAnchor from '@/components/ui-components/menus/MenusAnchor.vue';\nimport MenusHover from '@/components/ui-components/menus/MenusHover.vue';\nimport MenusActivatorTooltip from '@/components/ui-components/menus/MenusActivatorTooltip.vue';\nimport MenusPopover from '@/components/ui-components/menus/MenusPopover.vue';\n\nconst page = ref({ title: 'Menus' });\nconst breadcrumbs = ref([\n  {\n    text: 'Dashboard',\n    disabled: false,\n    href: '#',\n  },\n  {\n    text: 'Menus',\n    disabled: true,\n    href: '#',\n  },\n]);\n</script>\n\n<template>\n  <BaseBreadcrumb :title=\"page.title\" :breadcrumbs=\"breadcrumbs\"></BaseBreadcrumb>\n\n  <UiParentCard title=\"Menus\">\n    <v-row>\n      <v-col cols=\"12\" sm=\"12\" lg=\"6\">\n        <UiChildCard title=\"Anchor\">\n          <MenusAnchor />\n        </UiChildCard>\n      </v-col>\n      <v-col cols=\"12\" sm=\"12\" lg=\"6\">\n        <UiChildCard title=\"Hover\">\n          <MenusHover />\n        </UiChildCard>\n      </v-col>\n      <v-col cols=\"12\" sm=\"12\" lg=\"6\">\n        <UiChildCard title=\"Activator and tooltip\">\n          <MenusActivatorTooltip />\n        </UiChildCard>\n      </v-col>\n      <v-col cols=\"12\" sm=\"12\" lg=\"6\">\n        <UiChildCard title=\"Popover\">\n          <MenusPopover />\n        </UiChildCard>\n      </v-col>\n    </v-row>\n  </UiParentCard>\n</template>\n"],"version":3}